arviz/__init__.py
arviz/labels.py
arviz/py.typed
arviz/rcparams.py
arviz/sel_utils.py
arviz/utils.py
arviz/data/__init__.py
arviz/data/base.py
arviz/data/converters.py
arviz/data/datasets.py
arviz/data/inference_data.py
arviz/data/io_cmdstan.py
arviz/data/io_cmdstanpy.py
arviz/data/io_dict.py
arviz/data/io_emcee.py
arviz/data/io_json.py
arviz/data/io_netcdf.py
arviz/data/io_numpyro.py
arviz/data/io_pyjags.py
arviz/data/io_pymc3.py
arviz/data/io_pymc3_3x.py
arviz/data/io_pyro.py
arviz/data/io_pystan.py
arviz/data/utils.py
arviz/data/_datasets/centered_eight.nc
arviz/data/_datasets/non_centered_eight.nc
arviz/plots/__init__.py
arviz/plots/autocorrplot.py
arviz/plots/bpvplot.py
arviz/plots/compareplot.py
arviz/plots/densityplot.py
arviz/plots/distcomparisonplot.py
arviz/plots/distplot.py
arviz/plots/dotplot.py
arviz/plots/ecdfplot.py
arviz/plots/elpdplot.py
arviz/plots/energyplot.py
arviz/plots/essplot.py
arviz/plots/forestplot.py
arviz/plots/hdiplot.py
arviz/plots/kdeplot.py
arviz/plots/khatplot.py
arviz/plots/lmplot.py
arviz/plots/loopitplot.py
arviz/plots/mcseplot.py
arviz/plots/pairplot.py
arviz/plots/parallelplot.py
arviz/plots/plot_utils.py
arviz/plots/posteriorplot.py
arviz/plots/ppcplot.py
arviz/plots/rankplot.py
arviz/plots/separationplot.py
arviz/plots/traceplot.py
arviz/plots/tsplot.py
arviz/plots/violinplot.py
arviz/plots/backends/__init__.py
arviz/plots/backends/bokeh/__init__.py
arviz/plots/backends/bokeh/autocorrplot.py
arviz/plots/backends/bokeh/bpvplot.py
arviz/plots/backends/bokeh/compareplot.py
arviz/plots/backends/bokeh/densityplot.py
arviz/plots/backends/bokeh/distcomparisonplot.py
arviz/plots/backends/bokeh/distplot.py
arviz/plots/backends/bokeh/dotplot.py
arviz/plots/backends/bokeh/ecdfplot.py
arviz/plots/backends/bokeh/elpdplot.py
arviz/plots/backends/bokeh/energyplot.py
arviz/plots/backends/bokeh/essplot.py
arviz/plots/backends/bokeh/forestplot.py
arviz/plots/backends/bokeh/hdiplot.py
arviz/plots/backends/bokeh/kdeplot.py
microarviz-0.13.0.dev0.dist-info/LICENSE
microarviz-0.13.0.dev0.dist-info/METADATA
microarviz-0.13.0.dev0.dist-info/WHEEL
microarviz-0.13.0.dev0.dist-info/top_level.txt
microarviz-0.13.0.dev0.dist-info/RECORD
