Metadata-Version: 2.1
Name: microarviz
Version: 0.13.0.dev0
Summary: Exploratory analysis of Bayesian models
Home-page: http://github.com/twiecki/microarviz
Author: ArviZ Developers
License: Apache-2.0
Platform: UNKNOWN
Classifier: Development Status :: 4 - Beta
Classifier: Framework :: Matplotlib
Classifier: Intended Audience :: Science/Research
Classifier: Intended Audience :: Education
Classifier: License :: OSI Approved :: Apache Software License
Classifier: Programming Language :: Python
Classifier: Programming Language :: Python :: 3
Classifier: Programming Language :: Python :: 3.7
Classifier: Programming Language :: Python :: 3.8
Classifier: Programming Language :: Python :: 3.9
Classifier: Topic :: Scientific/Engineering
Classifier: Topic :: Scientific/Engineering :: Visualization
Classifier: Topic :: Scientific/Engineering :: Mathematics
Requires-Python: >=3.7
Requires-Dist: setuptools (>=38.4)
Requires-Dist: matplotlib (>=3.0)
Requires-Dist: numpy (>=1.12)
Requires-Dist: scipy (>=0.19)
Requires-Dist: packaging
Requires-Dist: pandas (>=0.23)
Requires-Dist: xarray (>=0.16.1)
Requires-Dist: typing-extensions (>=3.7.4.3)
Requires-Dist: xarray-einstats (>=0.2)
Provides-Extra: all
Requires-Dist: numba ; extra == 'all'
Requires-Dist: bokeh (<3.0,>=1.4.0) ; extra == 'all'
Requires-Dist: ujson ; extra == 'all'
Requires-Dist: dask[distributed] ; extra == 'all'
Requires-Dist: zarr (>=2.5.0) ; extra == 'all'
